kibom/__init__.py
kibom/__main__.py
kibom/bom_writer.py
kibom/columns.py
kibom/component.py
kibom/csv_writer.py
kibom/debug.py
kibom/html_writer.py
kibom/netlist_reader.py
kibom/preferences.py
kibom/sort.py
kibom/units.py
kibom/version.py
kibom/xlsx_writer.py
kibom/xml_writer.py
kibom-1.9.1.data/scripts/KiBOM_CLI.py
kibom-1.9.1.dist-info/LICENSE.md
kibom-1.9.1.dist-info/METADATA
kibom-1.9.1.dist-info/WHEEL
kibom-1.9.1.dist-info/entry_points.txt
kibom-1.9.1.dist-info/top_level.txt
kibom-1.9.1.dist-info/RECORD
