Metadata-Version: 2.1
Name: kibom
Version: 1.9.1
Summary: Bill of Materials generation tool for KiCad EDA
Home-page: https://github.com/SchrodingersGat/KiBom
Author: Oliver Walters
Author-email: oliver.henry.walters@gmail.com
License: MIT
Keywords: kicad,bom,electronics,schematic,bill of materials
Requires-Python: >=2.7
License-File: LICENSE.md
Requires-Dist: xlsxwriter
